ghost/__init__.py
ghost/chat.py
ghost/cli.py
ghost/config.py
ghost/console.py
ghost/init.py
ghost/main.py
ghost/providers.py
ghost/rate_limiter.py
ghost/runner.py
ghost/spinner.py
ghosttest-0.2.2.2.dist-info/METADATA
ghosttest-0.2.2.2.dist-info/WHEEL
ghosttest-0.2.2.2.dist-info/entry_points.txt
ghosttest-0.2.2.2.dist-info/licenses/LICENSE
ghosttest-0.2.2.2.dist-info/RECORD
