Metadata-Version: 2.4
Name: ghosttest
Version: 0.2.2.2
Summary: An autonomous local-first AI agent that generates, executes, and self-heals Python unit tests in real-time.
Project-URL: Homepage, https://github.com/tripathiji1312/ghost/tree/main
Project-URL: Documentation, https://github.com/tripathiji1312/ghost/tree/main#readme
Project-URL: Repository, https://github.com/tripathiji1312/ghost/tree/main
Project-URL: Issues, https://github.com/tripathiji1312/ghost/issues
Author: Swarnim Tripathi
License: MIT
License-File: LICENSE
Keywords: ai-agent,developer-tools,groq,llm,ollama,pytest,qa,self-healing,test-automation,testing
Classifier: Development Status :: 4 - Beta
Classifier: Environment :: Console
Classifier: Framework :: Pytest
Classifier: Intended Audience :: Developers
Classifier: License :: OSI Approved :: MIT License
Classifier: Operating System :: OS Independent
Classifier: Programming Language :: Python :: 3.10
Classifier: Programming Language :: Python :: 3.11
Classifier: Topic :: Scientific/Engineering :: Artificial Intelligence
Classifier: Topic :: Software Development :: Quality Assurance
Classifier: Topic :: Software Development :: Testing
Requires-Python: >=3.10
Requires-Dist: anthropic>=0.18.0
Requires-Dist: click>=8.0.0
Requires-Dist: groq>=0.37.1
Requires-Dist: openai>=1.0.0
Requires-Dist: pytest>=7.0.0
Requires-Dist: python-dotenv>=1.0.0
Requires-Dist: requests>=2.28.0
Requires-Dist: rich>=13.0.0
Requires-Dist: watchdog>=3.0.0
Provides-Extra: dev
Requires-Dist: black; extra == 'dev'
Requires-Dist: isort; extra == 'dev'
Requires-Dist: mypy; extra == 'dev'
Requires-Dist: ruff; extra == 'dev'
